pixel_pretender/__init__.py
pixel_pretender/pixel_pretender.py
pixel_pretender-1.0.1.dist-info/LICENSE .txt
pixel_pretender-1.0.1.dist-info/METADATA
pixel_pretender-1.0.1.dist-info/WHEEL
pixel_pretender-1.0.1.dist-info/top_level.txt
pixel_pretender-1.0.1.dist-info/RECORD
