Metadata-Version: 2.1
Name: pixel_pretender
Version: 1.0.1
Summary: Render pixelated text in the console using customizable symbols and colors.
Home-page: https://github.com/AnasseGX/Pixel_pretender
Author: Anasse Gassab
Author-email: anasse.gsb@gmail.com
Keywords: ASCII Unicode pixel art terminal text rendering color formatting
Classifier: Programming Language :: Python :: 3
Classifier: License :: OSI Approved :: MIT License
Classifier: Operating System :: OS Independent
Requires-Python: >=3.8.0
License-File: LICENSE .txt
Requires-Dist: colorama>=0.4.6
Requires-Dist: rich<14.0.0,>=13.9.0
